odoo/addons/stock_picking_batch_weighing/README.rst
odoo/addons/stock_picking_batch_weighing/__init__.py
odoo/addons/stock_picking_batch_weighing/__manifest__.py
odoo/addons/stock_picking_batch_weighing/i18n/es.po
odoo/addons/stock_picking_batch_weighing/i18n/stock_picking_batch_weighing.pot
odoo/addons/stock_picking_batch_weighing/models/__init__.py
odoo/addons/stock_picking_batch_weighing/models/stock_move.py
odoo/addons/stock_picking_batch_weighing/models/stock_picking_batch.py
odoo/addons/stock_picking_batch_weighing/readme/CONTRIBUTORS.md
odoo/addons/stock_picking_batch_weighing/readme/DESCRIPTION.md
odoo/addons/stock_picking_batch_weighing/static/description/icon.png
odoo/addons/stock_picking_batch_weighing/static/description/index.html
odoo/addons/stock_picking_batch_weighing/views/stock_picking_batch_views.xml
odoo/addons/stock_picking_batch_weighing/wizards/__init__.py
odoo/addons/stock_picking_batch_weighing/wizards/weigh_operation_selection.py
odoo_addon_stock_picking_batch_weighing-15.0.1.0.1.dist-info/METADATA
odoo_addon_stock_picking_batch_weighing-15.0.1.0.1.dist-info/WHEEL
odoo_addon_stock_picking_batch_weighing-15.0.1.0.1.dist-info/top_level.txt
odoo_addon_stock_picking_batch_weighing-15.0.1.0.1.dist-info/RECORD
